bcpyaz/__init__.py
bcpyaz/binary_callers.py
bcpyaz/data_objects.py
bcpyaz/format_file_builder.py
bcpyaz/tmp_file.py
tests/__init__.py
tests/test_basic.py
tests/test_flat_file.py
tests/test_pandas.py
bcpyaz-0.2.0.dist-info/LICENSE
bcpyaz-0.2.0.dist-info/METADATA
bcpyaz-0.2.0.dist-info/WHEEL
bcpyaz-0.2.0.dist-info/top_level.txt
bcpyaz-0.2.0.dist-info/RECORD
