Metadata-Version: 2.1
Name: bcpyaz
Version: 0.2.0
Summary: Microsoft SQL Server bcp (Bulk Copy) wrapper with Azure Synapse Blob alternative
Home-page: https://github.com/Arcturus-io/bcpyaz
Author: Arcturus
Author-email: dan@arcturus.io
License: UNKNOWN
Keywords: bcp mssql
Platform: UNKNOWN
Classifier: Topic :: Database
Classifier: Programming Language :: Python :: 3
Classifier: Programming Language :: SQL
Classifier: License :: OSI Approved :: MIT License
Classifier: Operating System :: OS Independent
